fastsom/__init__.py
fastsom/interp.py
fastsom/log.py
fastsom/metrics.py
fastsom/callback/__init__.py
fastsom/callback/decorators.py
fastsom/callback/plotly_utils.py
fastsom/callback/training.py
fastsom/callback/viz.py
fastsom/core/__init__.py
fastsom/core/decorators.py
fastsom/core/tensor.py
fastsom/core/utils.py
fastsom/learn/__init__.py
fastsom/learn/initializers.py
fastsom/learn/learn.py
fastsom/learn/loss.py
fastsom/learn/optim.py
fastsom/learn/utils.py
fastsom/som/__init__.py
fastsom/som/distance.py
fastsom/som/neighborhood.py
fastsom/som/som.py
fastsom/viz/__init__.py
fastsom-1.0.2.dist-info/LICENSE
fastsom-1.0.2.dist-info/METADATA
fastsom-1.0.2.dist-info/WHEEL
fastsom-1.0.2.dist-info/top_level.txt
fastsom-1.0.2.dist-info/RECORD
